urirouter
