Metadata-Version: 2.1
Name: URIRouter
Version: 1.0.3
Summary: Flask-style routing for URIs
Home-page: https://github.com/The-Nicholas-R-Barrow-Company-LLC/uri-router
Author: The Nicholas R. Barrow Company, LLC
Author-email: me@nicholasrbarrow.com
License: MIT
Project-URL: Source, https://github.com/The-Nicholas-R-Barrow-Company-LLC/uri-router
Project-URL: Tracker, https://github.com/The-Nicholas-R-Barrow-Company-LLC/uri-router/issues
Platform: UNKNOWN
Classifier: License :: OSI Approved :: MIT License
Classifier: Programming Language :: Python :: 3
Classifier: Programming Language :: Python :: 3.8
License-File: LICENSE
